instill/api.py
instill/color.py
instill/drop.py
instill/formula.py
instill/log.py
instill/recipient.py
instill/tool.py
instill/util.py
instill/version.py
instill-0.1.1.dist-info/LICENSE
instill-0.1.1.dist-info/METADATA
instill-0.1.1.dist-info/WHEEL
instill-0.1.1.dist-info/entry_points.txt
instill-0.1.1.dist-info/top_level.txt
instill-0.1.1.dist-info/RECORD
